tydi/__init__.py
tydi/dispatch.py
tydi/inspectors/__init__.py
tydi/inspectors/class_inspector.py
tydi/inspectors/method_inspector.py
tydi/inspectors/module_inspector.py
tydi/multi_dispatch.py
tydi/overload.py
tydi/py.typed
tydi-0.2.1.dist-info/LICENSE
tydi-0.2.1.dist-info/METADATA
tydi-0.2.1.dist-info/WHEEL
tydi-0.2.1.dist-info/RECORD
