Metadata-Version: 2.1
Name: tydi
Version: 0.2.1
Summary: Multiple dispatch with type support
Author: Rama Krishna Reddy Gade
Author-email: you@example.com
Requires-Python: >=3.7,<4.0
Classifier: Programming Language :: Python :: 3
Classifier: Programming Language :: Python :: 3.7
Classifier: Programming Language :: Python :: 3.8
Classifier: Programming Language :: Python :: 3.9
Classifier: Programming Language :: Python :: 3.10
Classifier: Programming Language :: Python :: 3.11
Classifier: Programming Language :: Python :: 3.12
Requires-Dist: beartype (>=0.18.5,<0.19.0)
